circle_detection/py.typed
circle_detection/type_aliases.py
circle_detection/_circle_detection_cpp.cp313t-win_arm64.pyd
circle_detection/_circle_detector.py
circle_detection/_m_estimator.py
circle_detection/_ransac.py
circle_detection/__init__.py
circle_detection/operations/_circumferential_completeness_index.py
circle_detection/operations/_deduplicate_circles.py
circle_detection/operations/_non_maximum_suppression.py
circle_detection/operations/_operations_cpp.cp313t-win_arm64.pyd
circle_detection/operations/_select_top_k_circles.py
circle_detection/operations/__init__.py
circle_detection-1.0.0.dist-info/DELVEWHEEL
circle_detection-1.0.0.dist-info/METADATA
circle_detection-1.0.0.dist-info/RECORD
circle_detection-1.0.0.dist-info/WHEEL
circle_detection-1.0.0.dist-info/licenses/LICENSE
circle_detection.libs/libomp-6d13220eec11976576ed8cc072168a5d.dll
circle_detection.libs/msvcp140-9cb625fcbc2fbbd6fca1aee8b24b0ebe.dll
include/__init__.py
include/CircleDetection/circle_detection_m_estimator.h
include/CircleDetection/circle_detection_ransac.h
include/CircleDetection/loss_functions.h
include/CircleDetection/operations.h
include/CircleDetection/type_aliases.h
share/__init__.py
share/CircleDetection/cmake/CircleDetectionConfig.cmake
share/CircleDetection/cmake/CircleDetectionConfigVersion.cmake
