Metadata-Version: 2.2
Name: circle_detection
Version: 1.0.0
Summary: A Python package for detecting circles in 2D point sets.
Keywords: circle fitting,data science
Author-Email: Josafat-Mattias Burmeister <burmeister@uni-potsdam.de>
Maintainer-Email: Josafat-Mattias Burmeister <burmeister@uni-potsdam.de>
License: MIT License
Classifier: Development Status :: 4 - Beta
Classifier: License :: OSI Approved :: MIT License
Classifier: Programming Language :: Python
Classifier: Programming Language :: Python :: 3 :: Only
Classifier: Programming Language :: Python :: 3.9
Classifier: Programming Language :: Python :: 3.10
Classifier: Programming Language :: Python :: 3.11
Classifier: Programming Language :: Python :: 3.12
Classifier: Programming Language :: Python :: 3.13
Classifier: Programming Language :: Python :: 3.14
Project-URL: Homepage, https://github.com/josafatburmeister/circle_detection
Project-URL: Documentation, https://josafatburmeister.github.io/circle_detection/
Project-URL: Repository, https://github.com/josafatburmeister/circle_detection.git
Project-URL: Issues, https://github.com/josafatburmeister/circle_detection/issues
Project-URL: Changelog, https://josafatburmeister.github.io/circle_detection/changelog
Requires-Python: >=3.9
Requires-Dist: numpy<3.0.0,>=1.21.0
Provides-Extra: dev
Requires-Dist: clang-format; extra == "dev"
Requires-Dist: clang-tidy; extra == "dev"
Requires-Dist: black; extra == "dev"
Requires-Dist: mypy; extra == "dev"
Requires-Dist: pre-commit; extra == "dev"
Requires-Dist: pylint; extra == "dev"
Requires-Dist: pytest; extra == "dev"
Requires-Dist: pytest-cov; extra == "dev"
Provides-Extra: docs
Requires-Dist: sphinx; extra == "docs"
Requires-Dist: sphinx-autodoc-typehints; extra == "docs"
Requires-Dist: sphinx-copybutton; extra == "docs"
Requires-Dist: sphinx-design; extra == "docs"
Requires-Dist: sphinx-docsearch; extra == "docs"
Requires-Dist: sphinxawesome-theme; extra == "docs"
Requires-Dist: sphinx-sitemap; extra == "docs"
Requires-Dist: sphinxcontrib-jsmath; extra == "docs"
Requires-Dist: sphinxcontrib-katex; extra == "docs"
Requires-Dist: sphinxcontrib-napoleon; extra == "docs"
Requires-Dist: sphinx_mdinclude; extra == "docs"
